vegasflow/__init__.py
vegasflow/configflow.py
vegasflow/monte_carlo.py
vegasflow/plain.py
vegasflow/utils.py
vegasflow/vflow.py
vegasflow/vflowplus.py
vegasflow/tests/__init__.py
vegasflow/tests/test_algs.py
vegasflow/tests/test_config.py
vegasflow/tests/test_gradients.py
vegasflow/tests/test_misc.py
vegasflow/tests/test_utils.py
vegasflow-1.3.0.dist-info/LICENSE
vegasflow-1.3.0.dist-info/METADATA
vegasflow-1.3.0.dist-info/WHEEL
vegasflow-1.3.0.dist-info/top_level.txt
vegasflow-1.3.0.dist-info/RECORD
