Metadata-Version: 2.1
Name: vegasflow
Version: 1.3.0
Summary: Monte Carlo integration with Tensorflow
Home-page: https://github.com/N3PDF/VegasFlow
Author: S.Carrazza, J.Cruz-Martinez
Author-email: stefano.carrazza@cern.ch, juan.cruz@mi.infn.it
License: UNKNOWN
Platform: UNKNOWN
Classifier: Operating System :: Unix
Classifier: Programming Language :: Python
Classifier: Programming Language :: Python :: 3
Classifier: Topic :: Scientific/Engineering
Classifier: Topic :: Scientific/Engineering :: Physics
Requires-Python: >=3.9
License-File: LICENSE
Requires-Dist: joblib
Requires-Dist: numpy
Requires-Dist: tensorflow
Provides-Extra: benchmark
Requires-Dist: vegas ; extra == 'benchmark'
Provides-Extra: distribute
Requires-Dist: dask ; extra == 'distribute'
Requires-Dist: distributed ; extra == 'distribute'
Requires-Dist: dask-jobqueue ; extra == 'distribute'
Requires-Dist: tensorflow (>2.2) ; extra == 'distribute'
Provides-Extra: docs
Requires-Dist: sphinx-rtd-theme ; extra == 'docs'
Requires-Dist: recommonmark ; extra == 'docs'
Requires-Dist: sphinxcontrib-bibtex ; extra == 'docs'
Provides-Extra: examples
Requires-Dist: cffi ; extra == 'examples'
Requires-Dist: pineappl ; extra == 'examples'
Requires-Dist: pdfflow ; extra == 'examples'
Requires-Dist: scipy ; extra == 'examples'
